{"time": "futebol", "title": ["Triunfo tranquiliza ambiente, e conversa por Denilson fica perto de ser finalizada", "Sequ\u00eancia de resultados ruins do Atl\u00e9tico-MG pausou negocia\u00e7\u00e3o com atacante do Vit\u00f3ria, que est\u00e1 pr\u00f3ximo de acertar com o Atl\u00e9tico-MG"], "author": ["Rafael Ara\u00fajo"], "text": " O Atl\u00e9tico-MG reencontrou o caminho das vit\u00f3rias no cl\u00e1ssico contra o Am\u00e9rica-MG e amenizou o clima ruim ap\u00f3s uma sequ\u00eancia de tr\u00eas partidas seguidas sem vencer. O que tamb\u00e9m dever\u00e1 retornar s\u00e3o as conversas do Galo com o atacante Denilson, que est\u00e1 no Vit\u00f3ria, mas pertence ao Granada, da Espanha.    As negocia\u00e7\u00f5es entre as partes est\u00e3o bem adiantadas, mas travaram por causa do momento ruim do Atl\u00e9tico-MG no Campeonato Brasileiro. Com a retomada alvinegra, represantes do jogador devem conversar com os dirigentes do Galo para fazer o acerto final.  Denilson n\u00e3o entra em campo h\u00e1 tr\u00eas partidas pelo Vit\u00f3ria, justamente , impedindo-o de jogar por qualquer outra equipe na edi\u00e7\u00e3o deste ano da competi\u00e7\u00e3o. ", "date": "08/06/2018", "id": 748}